ptextpad/__init__.py
ptextpad/__main__.py
ptextpad/__main__.py-
ptextpad/align_blocks_final.py
ptextpad/align_sent.py
ptextpad/align_text.py
ptextpad/amend_avec.py
ptextpad/chardet_file.py
ptextpad/clapse_text.py
ptextpad/csv_to_list.py
ptextpad/data_for_updating.py
ptextpad/detect_file.py
ptextpad/detect_lang.py
ptextpad/docx_to_text.py
ptextpad/docx_to_txt.py
ptextpad/element_to_string.py
ptextpad/en_zh_separation.py
ptextpad/epub_to_txt.py
ptextpad/fetch_url.py
ptextpad/fetch_url_ui.py
ptextpad/fetch_xpath.py
ptextpad/gen_aligned_sentlist.py
ptextpad/get_anchor_set.py
ptextpad/get_para.py
ptextpad/help_manual.py
ptextpad/html2txt.py
ptextpad/insert_itag.py
ptextpad/list_to_csv.py
ptextpad/list_to_selected_rows.py
ptextpad/lists_to_tmx4n.py
ptextpad/load_file_as_text.py
ptextpad/load_text.py
ptextpad/load_zipped.py
ptextpad/loadtext.py
ptextpad/logging_progress.py
ptextpad/minifuncwrapper.py
ptextpad/mlbee_client.py
ptextpad/msg_popup.py
ptextpad/myqprogressbar.py
ptextpad/mytable-looks-ok.py-
ptextpad/mytable.py
ptextpad/mytable1.py-
ptextpad/neualigner.py-
ptextpad/neualigner_ui.py-
ptextpad/ofiles_2files.py
ptextpad/para_cosine_rev.py
ptextpad/para_gc.py
ptextpad/pdf_to_text.py
ptextpad/pdf_to_text_h.py
ptextpad/popup_anchortab_dirty.py
ptextpad/post_process.py
ptextpad/ptextpad.py
ptextpad/pyqtlogging.py
ptextpad/qdialog_ptextpad.py
ptextpad/qthread_func_with_progressbar.py
ptextpad/readme.html
ptextpad/realign_list.py
ptextpad/realign_selected_rows.py
ptextpad/realign_sent_list.py
ptextpad/reanchor_selected_rows.py
ptextpad/remove_selected_rows.py
ptextpad/resource.qrc
ptextpad/resource_rc.py
ptextpad/runnable.py
ptextpad/seg_chinese.py
ptextpad/seg_sent.py
ptextpad/seg_xysent.py
ptextpad/seg_zhsent.py
ptextpad/select_last_selected_rows.py
ptextpad/send_to_table.py
ptextpad/sep_chinese.py
ptextpad/set_anchor.py
ptextpad/set_anchor_extra_outputs.py
ptextpad/singlehtml/.buildinfo
ptextpad/singlehtml/_images/alignbut.png
ptextpad-0.1.0a6.dist-info/entry_points.txt
ptextpad-0.1.0a6.dist-info/LICENSE
ptextpad-0.1.0a6.dist-info/WHEEL
ptextpad-0.1.0a6.dist-info/METADATA
ptextpad-0.1.0a6.dist-info/RECORD
