Metadata-Version: 2.1
Name: ptextpad
Version: 0.1.0a6
Summary: ptextpad
Home-page: https://github.com/ffreemt/ptextpad
License: MIT
Author: ffreemt
Requires-Python: >=3.8.3,<4.0.0
Classifier: License :: OSI Approved :: MIT License
Classifier: Programming Language :: Python :: 3
Classifier: Programming Language :: Python :: 3.10
Classifier: Programming Language :: Python :: 3.9
Requires-Dist: PyQt5 (>=5.15.7,<6.0.0)
Requires-Dist: about-time (>=4.1.0,<5.0.0)
Requires-Dist: cchardet (>=2.1.7,<3.0.0)
Requires-Dist: chardet (>=4.0.0,<5.0.0)
Requires-Dist: fastlid (>=0.1.7,<0.2.0)
Requires-Dist: html2text (>=2020.1.16,<2021.0.0)
Requires-Dist: icecream (>=2.1.1,<3.0.0)
Requires-Dist: install (>=1.3.5,<2.0.0)
Requires-Dist: logzero (>=1.7.0,<2.0.0)
Requires-Dist: nltk (>=3.7,<4.0)
Requires-Dist: nose (>=1.3.7,<2.0.0)
Requires-Dist: pandas (>=1.4.3,<2.0.0)
Requires-Dist: pysrt (>=1.1.2,<2.0.0)
Requires-Dist: pysubs2 (>=1.4.2,<2.0.0)
Requires-Dist: python-docx (>=0.8.11,<0.9.0)
Requires-Dist: radio-mlbee-client (>=0.1.0a0,<0.2.0)
Requires-Dist: requests (>=2.28.1,<3.0.0)
Requires-Dist: seg-text (>=0.1.2,<0.2.0)
Requires-Dist: set-loglevel (>=0.1.2,<0.2.0)
Requires-Dist: stop-thread (>=0.1.0,<0.2.0)
Project-URL: Repository, https://github.com/ffreemt/ptextpad
